LICENSE
README.md
setup.py
mbs/__init__.py
mbs/corrections.py
mbs/io.py
mbs/krx.py
mbs/resolution.py
mbs/spectra.py
mbs/utils.py
mbs/widgets.py
mbsutils.egg-info/PKG-INFO
mbsutils.egg-info/SOURCES.txt
mbsutils.egg-info/dependency_links.txt
mbsutils.egg-info/not-zip-safe
mbsutils.egg-info/requires.txt
mbsutils.egg-info/top_level.txt